{"chrome://browser/content/browser.xhtml":{"main-window":{"sizemode":"maximized","screenX":"45","screenY":"45","width":"960","height":"1040"},"sidebar-box":{"style":"order: 2;"},"sidebar-title":{"value":"Bitwarden"},"toolbar-menubar":{"autohide":"true"}},"chrome://browser/content/places/places.xhtml":{"placesContentTags":{"ordinal":"3"},"placesContentUrl":{"ordinal":"5"},"placesContentDate":{"ordinal":"7"},"placesContentVisitCount":{"ordinal":"9"},"placesContentDateAdded":{"ordinal":"11"},"placesContentLastModified":{"ordinal":"13"},"places":{"screenX":"0","screenY":"0","width":"800","height":"500","sizemode":"normal"}}}